.gitignore
.gitmodules
.pre-commit-config.yaml
CMakeLists.txt
LICENSE
MANIFEST.in
README.md
lgtm.yml
pyproject.toml
requirements.txt
setup.cfg
setup.py
.github/workflows/conda.yml
.github/workflows/python-package.yml
.github/workflows/python-publish.yml
MULTEM/.git
MULTEM/.gitignore
MULTEM/LICENSE.txt
MULTEM/README.md
MULTEM/compile_mex_multem.m
MULTEM/startup.m
MULTEM/crystalline_materials/Ag001_xtl.m
MULTEM/crystalline_materials/Ag110_xtl.m
MULTEM/crystalline_materials/Al001_xtl.m
MULTEM/crystalline_materials/Al110_xtl.m
MULTEM/crystalline_materials/Au001_xtl.m
MULTEM/crystalline_materials/Au110_xtl.m
MULTEM/crystalline_materials/Cu001_xtl.m
MULTEM/crystalline_materials/Cu110_xtl.m
MULTEM/crystalline_materials/Diamond110_xtl.m
MULTEM/crystalline_materials/GaAs001_xtl.m
MULTEM/crystalline_materials/Ir001_xtl.m
MULTEM/crystalline_materials/Ir110_xtl.m
MULTEM/crystalline_materials/LaAlO3001_xtl.m
MULTEM/crystalline_materials/Mo001_xtl.m
MULTEM/crystalline_materials/Ni001_xtl.m
MULTEM/crystalline_materials/Ni110_xtl.m
MULTEM/crystalline_materials/Pb001_xtl.m
MULTEM/crystalline_materials/Pb110_xtl.m
MULTEM/crystalline_materials/Pd001_xtl.m
MULTEM/crystalline_materials/Pd110_xtl.m
MULTEM/crystalline_materials/PdH001_xtl.m
MULTEM/crystalline_materials/Primitive_xtl.m
MULTEM/crystalline_materials/Pt001_xtl.m
MULTEM/crystalline_materials/Pt110_xtl.m
MULTEM/crystalline_materials/Si001_xtl.m
MULTEM/crystalline_materials/Si110_xtl.m
MULTEM/crystalline_materials/SrTiO3001_xtl.m
MULTEM/crystalline_materials/SrTiO3110_xtl.m
MULTEM/crystalline_materials/YH2001_xtl.m
MULTEM/crystalline_materials/fcc001_xtl.m
MULTEM/crystalline_materials/fcc110_xtl.m
MULTEM/crystalline_materials/graphene.m
MULTEM/gui_multem/main.cpp
MULTEM/gui_multem/mainwindow.cpp
MULTEM/gui_multem/mainwindow.h
MULTEM/gui_multem/multem.cu
MULTEM/gui_multem/multem.cuh
MULTEM/gui_multem/multem.pro
MULTEM/gui_multem/multem.pro.user
MULTEM/gui_multem/multem.qrc
MULTEM/gui_multem/q_colormap.h
src/python_multem.egg-info/PKG-INFO
src/python_multem.egg-info/SOURCES.txt
src/python_multem.egg-info/dependency_links.txt
src/python_multem.egg-info/requires.txt
src/python_multem.egg-info/top_level.txt
