Metadata-Version: 2.4
Name: python-multem
Version: 0.4.1
Summary: A Python wrapper for MULTEM
Home-page: https://github.com/rosalindfranklininstitute/python-multem
Author: James Parkhurst
Author-email: james.parkhurst@diamond.ac.uk
License: GPL v3
Project-URL: Source, https://github.com/rosalindfranklininstitute/python-multem
Project-URL: Tracker, https://github.com/rosalindfranklininstitute/python-multem/issues
Keywords: MULTEM
Platform: unix
Platform: linux
Platform: osx
Platform: cygwin
Platform: win32
Classifier: Development Status :: 4 - Beta
Classifier: Intended Audience :: Developers
Classifier: Operating System :: POSIX
Classifier: Operating System :: Microsoft :: Windows
Classifier: Operating System :: MacOS :: MacOS X
Classifier: Topic :: Utilities
Classifier: Programming Language :: Python :: 3.4
Classifier: Programming Language :: Python :: 3.5
Classifier: Programming Language :: Python :: 3.6
Classifier: Programming Language :: Python :: 3.7
License-File: LICENSE
Requires-Dist: numpy
Provides-Extra: build-sphinx
Requires-Dist: sphinx; extra == "build-sphinx"
Requires-Dist: sphinx_rtd_theme; extra == "build-sphinx"
Provides-Extra: test
Requires-Dist: pytest; extra == "test"
Requires-Dist: pytest-cov; extra == "test"
Requires-Dist: mock; extra == "test"
Dynamic: license-file
Dynamic: provides-extra
Dynamic: requires-dist
